{
  "@context": {
    "@vocab": "https://schema.org/"
  },
  "@id": "49UF20130107_bottle",
  "@type": "Dataset",
  "variableMeasured": [
    {
      "@type": "PropertyValue",
      "name": "time",
      "propertyID": "http://vocab.nerc.ac.uk/standard_name/time",
      "minValue": 1357736340,
      "maxValue": 1358378280
    },
    {
      "@type": "PropertyValue",
      "name": "latitude",
      "propertyID": "http://vocab.nerc.ac.uk/standard_name/latitude",
      "unitsText": "degree_north",
      "minValue": 23.734,
      "maxValue": 28.6978
    },
    {
      "@type": "PropertyValue",
      "name": "longitude",
      "propertyID": "http://vocab.nerc.ac.uk/standard_name/longitude",
      "unitsText": "degree_east",
      "minValue": 126.4483,
      "maxValue": 136.9838
    },
    {
      "@type": "PropertyValue",
      "name": "btm_depth",
      "propertyID": "http://vocab.nerc.ac.uk/standard_name/sea_floor_depth_below_sea_surface",
      "unitsText": "meters",
      "minValue": 142.0,
      "maxValue": 6231.0
    },
    {
      "@type": "PropertyValue",
      "name": "pressure",
      "propertyID": "http://vocab.nerc.ac.uk/standard_name/sea_water_pressure",
      "unitsText": "dbar",
      "minValue": 0.0,
      "maxValue": 6121.7
    },
    {
      "@type": "PropertyValue",
      "name": "ctd_temperature",
      "propertyID": "http://vocab.nerc.ac.uk/standard_name/sea_water_temperature",
      "unitsText": "degC",
      "minValue": 1.5116,
      "maxValue": 24.1688
    },
    {
      "@type": "PropertyValue",
      "name": "ctd_salinity",
      "propertyID": "http://vocab.nerc.ac.uk/standard_name/sea_water_practical_salinity",
      "unitsText": "1",
      "minValue": 34.1185,
      "maxValue": 34.8662
    },
    {
      "@type": "PropertyValue",
      "name": "bottle_salinity",
      "propertyID": "http://vocab.nerc.ac.uk/standard_name/sea_water_practical_salinity",
      "unitsText": "1",
      "minValue": 34.1381,
      "maxValue": 34.8557
    },
    {
      "@type": "PropertyValue",
      "name": "oxygen",
      "propertyID": "http://vocab.nerc.ac.uk/standard_name/moles_of_oxygen_per_unit_mass_in_sea_water",
      "unitsText": "umol/kg",
      "minValue": 54.6,
      "maxValue": 222.6
    },
    {
      "@type": "PropertyValue",
      "name": "silicate",
      "propertyID": "http://vocab.nerc.ac.uk/standard_name/moles_of_silicate_per_unit_mass_in_sea_water",
      "unitsText": "umol/kg",
      "minValue": 0.14,
      "maxValue": 142.12
    },
    {
      "@type": "PropertyValue",
      "name": "nitrate",
      "propertyID": "http://vocab.nerc.ac.uk/standard_name/moles_of_nitrate_per_unit_mass_in_sea_water",
      "unitsText": "umol/kg",
      "minValue": -0.08,
      "maxValue": 40.92
    },
    {
      "@type": "PropertyValue",
      "name": "nitrite",
      "propertyID": "http://vocab.nerc.ac.uk/standard_name/moles_of_nitrite_per_unit_mass_in_sea_water",
      "unitsText": "umol/kg",
      "minValue": 0.0,
      "maxValue": 0.47
    },
    {
      "@type": "PropertyValue",
      "name": "phosphate",
      "propertyID": "http://vocab.nerc.ac.uk/standard_name/moles_of_phosphate_per_unit_mass_in_sea_water",
      "unitsText": "umol/kg",
      "minValue": 0.0,
      "maxValue": 2.89
    },
    {
      "@type": "PropertyValue",
      "name": "total_carbon",
      "propertyID": "http://vocab.nerc.ac.uk/standard_name/moles_of_dissolved_inorganic_carbon_per_unit_mass_in_sea_water",
      "unitsText": "umol/kg",
      "minValue": 1954.7,
      "maxValue": 2355.1
    },
    {
      "@type": "PropertyValue",
      "name": "ph_total_h_scale",
      "propertyID": "http://vocab.nerc.ac.uk/standard_name/sea_water_ph_reported_on_total_scale",
      "unitsText": "1",
      "minValue": 7.3869,
      "maxValue": 8.0913
    },
    {
      "@type": "PropertyValue",
      "name": "ph_temperature",
      "propertyID": "http://vocab.nerc.ac.uk/standard_name/temperature_of_analysis_of_sea_water",
      "unitsText": "degC",
      "minValue": 25.0,
      "maxValue": 25.0
    },
    {
      "@type": "PropertyValue",
      "name": "bottle_time",
      "propertyID": "http://vocab.nerc.ac.uk/standard_name/time",
      "minValue": 1357736340,
      "maxValue": 1358380680
    }
  ]
}